{
  "multilingualAI": "Multilingual MedEcho AI",
  "aiConsultation": "AI Consultation",
  "confirmSelected": "Confirm Selected",
  "processingLive": "Processing Live",
  "other": "Other",
  "none": "None",
  "yesExperience": "Yes, I experience:",
  "otherSymptoms": "I am experiencing other symptoms",
  "noneOfThese": "None of these",
  "aiAssistantName": "MedEcho AI Assistant",
  "aiGreeting": "Hi! I am your MedEcho AI assistant. How can I help you today?",
  "aiContextReceived": "I've received the patient context. How can I assist?",
  "aiConnectError": "❌ Error connecting to AI service. Please ensure the backend and ML servers are running.",
  "aiChatTitle": "MedEcho Chat",
  "autoDetect": "Auto Detect",
  "aiWarning": "AI Assistant: Collecting clinical intake data in realtime.",
  "describeSymptoms": "Describe symptoms...",
  "listening": "Listening",
  "speakingResponse": "Speaking Response",
  "assistantThinking": "Assistant Thinking",
  "cancelVoice": "Cancel Voice",
  "uploadReport": "Upload Report",
  "aiSystemReady": "MedEcho AI Ready",
  "mode": "Mode",
  "quickChatIntake": "Quick Chat Intake Record",
  "consultHumanDoctor": "Please consult a human doctor for confirmation.",
  "reportGenQuickChat": "Report generated via quick chat assistant.",
  "standardPrecautions": "Standard precautions advised.",
  "saveReportError": "I couldn’t save your report. Please check your network connection.",
  "medEchoLogo": "MedEcho",
  "clinicalConsult": "Clinical Consultation",
  "aiMedicalIntake": "AI Medical Intake",
  "consultProfessional": "Please consult a medical professional for advice.",
  "unassigned": "Unassigned",
  "aiHubTitle": "AI Medical Research Hub",
  "voiceLocked": "Voice Input Locked",
  "voiceAnalyzing": "Audio analysis in progress...",
  "voiceAnalysisTitle": "Medical Audio Analysis",
  "voiceProcessing": "Processing speech patterns...",
  "contextLocked": "Medical context locked",
  "aiSynthesis": "AI Synthesis",
  "thinking": "Thinking",
  "speaking": "Speaking",
  "recommendedSpecialists": "Recommended Specialists",
  "consult": "Consult",
  "yesIExperience": "Yes, I experience:",
  "experiencingOther": "I am experiencing other symptoms",
  "mmhg": "mmHg",
  "kg": "kg",
  "mgdl": "mg/dL",
  "celsius": "°C",
  "voiceCall": "Voice Call",
  "videoCall": "Video Call",
  "incomingConsultation": "Incoming Consultation",
  "answer": "Answer",
  "decline": "Decline",
  "sttError": "Speech-to-text conversion failed. Please try typing.",
  "uploadError": "Failed to process document.",
  "aiServiceError": "Intelligence cluster unresponsive.",
  "profileSyncDesc": "Profile synchronized.",
  "micDenied": "Microphone access denied."
}